README.rst
setup.py
mmap_backed_array/__init__.py
mmap_backed_array/mmap_array.py
mmap_backed_array/slice_decoding.py
mmap_backed_array.egg-info/PKG-INFO
mmap_backed_array.egg-info/SOURCES.txt
mmap_backed_array.egg-info/dependency_links.txt
mmap_backed_array.egg-info/requires.txt
mmap_backed_array.egg-info/top_level.txt