Metadata-Version: 1.1
Name: mmap-backed-array
Version: 0.3.1
Summary: Arrays with mmap backing
Home-page: https://github.com/JaggedVerge/mmap_backed_array
Author: Janis Lesinskis
Author-email: janis@jaggedverge.com
License: GPLv3
Keywords: mmap array
Platform: UNKNOWN
Classifier: Development Status :: 4 - Beta
Classifier: Intended Audience :: Developers
Classifier: Programming Language :: Python
Classifier: Programming Language :: Python :: 3.3
Classifier: Programming Language :: Python :: 3.4
Classifier: Programming Language :: Python :: 3.5
